LICENSE
README.md
setup.py
finalize_plots/__init__.py
finalize_plots/finalize.py
finalize_plots.egg-info/PKG-INFO
finalize_plots.egg-info/SOURCES.txt
finalize_plots.egg-info/dependency_links.txt
finalize_plots.egg-info/requires.txt
finalize_plots.egg-info/top_level.txt
tests/__init__.py
tests/test.py