Metadata-Version: 2.1
Name: finalize-plots
Version: 0.0.1
Summary: essential on laptops
Download-URL: https://github.com/duxfrederic/finalize_plot/archive/refs/tags/v0.0.1.tar.gz
Author: Frédéric Dux
Author-email: duxfrederic@gmail.com
License: MIT
Platform: UNKNOWN
Requires-Python: >3.6.0
License-File: LICENSE
